{
  "subgraphs": [
    {
      "ops": [
        0
      ],
      "tensors_to_retain": [
        10
      ],
      "granularity": [
        128,
        32,
        128
      ]
    },
    {
      "ops": [
        1
      ],
      "tensors_to_retain": [
        11
      ],
      "granularity": [
        128,
        32,
        1
      ]
    },
    {
      "ops": [
        2
      ],
      "tensors_to_retain": [
        12
      ],
      "granularity": [
        128,
        32,
        128
      ]
    },
    {
      "ops": [
        3
      ],
      "tensors_to_retain": [
        13
      ],
      "granularity": [
        128,
        32,
        128
      ]
    },
    {
      "ops": [
        4
      ],
      "tensors_to_retain": [
        14
      ],
      "granularity": [
        128,
        32,
        1
      ]
    },
    {
      "ops": [
        5
      ],
      "tensors_to_retain": [
        15
      ],
      "granularity": [
        128,
        32,
        128
      ]
    },
    {
      "ops": [
        6
      ],
      "tensors_to_retain": [
        16
      ],
      "granularity": [
        128,
        32,
        1
      ]
    },
    {
      "ops": [
        7
      ],
      "tensors_to_retain": [
        17
      ],
      "granularity": [
        128,
        32,
        128
      ]
    },
    {
      "ops": [
        8
      ],
      "tensors_to_retain": [
        18
      ],
      "granularity": [
        128,
        32,
        128
      ]
    },
    {
      "ops": [
        9
      ],
      "tensors_to_retain": [
        19
      ],
      "granularity": [
        128,
        32,
        1
      ]
    },
    {
      "ops": [
        15
      ],
      "tensors_to_retain": [
        25
      ],
      "granularity": [
        128,
        32,
        1
      ]
    },
    {
      "ops": [
        10
      ],
      "tensors_to_retain": [
        20
      ],
      "granularity": [
        128,
        32,
        128
      ]
    },
    {
      "ops": [
        11
      ],
      "tensors_to_retain": [
        21
      ],
      "granularity": [
        128,
        32,
        1
      ]
    },
    {
      "ops": [
        12
      ],
      "tensors_to_retain": [
        22
      ],
      "granularity": [
        128,
        32,
        128
      ]
    },
    {
      "ops": [
        13
      ],
      "tensors_to_retain": [
        23
      ],
      "granularity": [
        128,
        32,
        128
      ]
    },
    {
      "ops": [
        14
      ],
      "tensors_to_retain": [
        24
      ],
      "granularity": [
        128,
        32,
        1
      ]
    },
    {
      "ops": [
        16
      ],
      "tensors_to_retain": [
        26
      ],
      "granularity": [
        128,
        32,
        1
      ]
    },
    {
      "ops": [
        17,
        18
      ],
      "tensors_to_retain": [
        28
      ],
      "granularity": [
        128,
        32,
        1
      ]
    }
  ]
}